HieDiff/__init__.py
HieDiff/_heatmap.py
HieDiff/_HieDiff.py
HieDiff/_HieDiff_minibatch.py
HieDiff/_karras_diffusion.py
HieDiff/_model_utils.py
HieDiff/_moduleW.py
HieDiff/_nn.py
HieDiff/_regulons.py
HieDiff/_scatterplots.py
HieDiff/_spatial.py
HieDiff/_spatial_reconstruction.py
HieDiff/_utils.py
hiediff-0.1.0.dist-info/METADATA
hiediff-0.1.0.dist-info/WHEEL
hiediff-0.1.0.dist-info/RECORD
